{
    "title": "Frogger - Part 3",
    "description": "In the third part of the Frogger coding challenge, I implement the rows of logs/turtles that the frog jumps onto.",
    "videoNumber": "72.3",
    "videoId": "hk326ZHlENQ",
    "date": "2017-06-16",
    "languages": [],
    "topics": [],
    "canContribute": true,
    "relatedChallenges": [],
    "timestamps": [],
    "codeExamples": [
        {
            "title": "p5js - p5 Web Editor",
            "description": "",
            "urls": {
                "p5": "https://editor.p5js.org/codingtrain/sketches/crMMFw8vD"
            }
        },
        {
            "title": "p5js - GitHub",
            "description": "",
            "urls": {
                "other": "https://github.com/CodingTrain/website/tree/main/CodingChallenges/CC_072_Frogger/P5"
            }
        },
        {
            "title": "Processing - Processing",
            "description": "",
            "urls": {
                "processing": "https://github.com/CodingTrain/website/tree/main/CodingChallenges/CC_072_Frogger/Processing"
            }
        }
    ],
    "groupLinks": [
        {
            "title": "Other Parts Of This Coding Challenge",
            "links": [
                {
                    "title": "Frogger - Part 1",
                    "url": "/CodingChallenges/072.1-frogger",
                    "description": ""
                },
                {
                    "title": "Frogger - Part 2",
                    "url": "/CodingChallenges/072.2-frogger",
                    "description": ""
                },
                {
                    "title": "Frogger - Part 4",
                    "url": "/CodingChallenges/072.4-frogger",
                    "description": ""
                }
            ]
        },
        {
            "title": "References",
            "links": [
                {
                    "title": "Frogger on Wikipedia",
                    "url": "https://en.wikipedia.org/wiki/Frogger",
                    "description": ""
                }
            ]
        },
        {
            "title": "Videos",
            "links": [
                {
                    "title": "Video of the Gameplay",
                    "url": "https://youtu.be/l9eTOaNFwKQ",
                    "description": ""
                }
            ]
        }
    ]
}