{
  "title": "Breadth-First Search",
  "description": "In this two part challenge, I implement the Breadth-First Search algorithm in JavaScript. My demo application is \"6 Degrees of Kevin Bacon\" (finding the closest relationship between Kevin Bacon and another actor).",
  "videoNumber": "68",
  "date": "2017-03-30",
  "languages": ["JavaScript", "p5.js"],
  "topics": ["breadth-first search algorithm", "Six Degrees of Kevin Bacon"],
  "canContribute": true,
  "relatedChallenges": ["65-binary-tree", "98-quadtree"],
  "timestamps": [],
  "parts": [
    {
      "title": "Part 1 - Creating a Graph",
      "videoId": "piBq7VD0ZSo",
      "timestamps": [
        {
          "time": "0:00",
          "title": "Introducing today's topic:  Breadth First Search"
        },
        { "time": "2:42", "title": "6 Degrees of Bacon" },
        { "time": "4:45", "title": "Node object" },
        { "time": "6:40", "title": "Let's Code!" },
        { "time": "8:02", "title": "Graph Object" },
        { "time": "9:44", "title": "Read the data" },
        {
          "time": "12:28",
          "title": "Attach a method to the graph object using prototype"
        },
        { "time": "16:52", "title": "Add an edges function" },
        {
          "time": "17:38",
          "title": "Determine whether actor node already exists"
        }
      ]
    },
    {
      "title": "Part 2 - Implementing the BFS Algorithm",
      "videoId": "-he67EEM6z0",
      "timestamps": [
        { "time": "0:00", "title": "Continuation of Breadth First Search" },
        { "time": "2:31", "title": "Add end and start node to graph object" },
        { "time": "4:35", "title": "Queue data structure" },
        {
          "time": "6:53",
          "title": "Write the code for the breadth first search algorithm"
        },
        { "time": "13:37", "title": "Find the path" },
        { "time": "16:59", "title": "Create a dropdown" },
        { "time": "20:04", "title": "Add reset function" }
      ]
    }
  ],
  "codeExamples": [
    {
      "title": "Breadth-First Search",
      "description": "This sketch implements the breadth first search algorithm.",
      "urls": { "p5": "https://editor.p5js.org/codingtrain/sketches/0_6EV76Qy" }
    }
  ],
  "groupLinks": [
    {
      "title": "References",
      "links": [
        {
          "icon": "📕",
          "title": "The Nature of Code Part 2 (Spring 2017) - Intelligence and Learning",
          "url": "https://github.com/nature-of-code/NOC-S17-2-Intelligence-Learning",
          "description": "Syllabus for Part 2 of Nature of Code: \"Intelligence and Learning\" at ITP Spring 2017"
        },
        {
          "icon": "📕",
          "title": "Nature of Code",
          "url": "https://github.com/nature-of-code/noc-book-2",
          "description": "Repository for The Nature of Code book with p5.js"
        },
        {
          "icon": "🥓",
          "title": "The Oracle of Bacon",
          "url": "http://oracleofbacon.org/",
          "description": "Website to determine the \"degrees of bacon\""
        },
        {
          "icon": "🗄",
          "title": "Breadth-First Search on Wikipedia",
          "url": "https://en.wikipedia.org/wiki/Breadth-first_search",
          "description": "Wikipedia page with background and references on the breadth-first search algorithm."
        },
        {
          "icon": "📘",
          "title": "Grokking Algorithms",
          "url": "https://www.manning.com/books/grokking-algorithms",
          "description": "An illustrated guide for programmers and other curious people."
        }
      ]
    },
    {
      "title": "Videos",
      "links": [
        {
          "icon": "🚂",
          "title": "My Video on Associative Arrays",
          "url": "https://youtu.be/_5jdE6RKxVk",
          "description": "In this video, I discuss the concept of \"associative arrays\" in JavaScript."
        },
        {
          "icon": "🚂",
          "title": "My Video on Prototypes",
          "url": "https://www.youtube.com/watch?v=hS_WqkyUah8",
          "description": "In this video, I examine the concept of \"Prototype\" in the JavaScript programming language."
        },
        {
          "icon": "🔴",
          "title": "Coding Train Live 88",
          "url": "https://youtu.be/YUlJAu1j_UM?t=4054s",
          "description": "Session 1 of “Intelligence and Learning and breadth-first-search"
        }
      ]
    }
  ],
  "credits": [
    { "title": "Editing", "name": "Mathieu Blanchette" },
    { "title": "Animations", "name": "Jason Heglund" }
  ]
}
