{
  "title": "4.2 Particle Emitters",
  "description": "In this video, I add an Emitter class to further organize the array of particles and allow for multiple particle systems in a p5.js sketch.",
  "languages": ["JavaScript", "p5.js"],
  "topics": ["For beginners"],
  "videoId": "wDYD3JVtOys",
  "timestamps": [
    { "time": "0:00", "title": "Welcome back!" },
    { "time": "0:28", "title": "Creating an Emitter class." },
    { "time": "1:32", "title": "Let's add update() and show()." },
    { "time": "2:37", "title": "Let's create an emitter in the sketch." },
    { "time": "3:20", "title": "How can we add particles." },
    { "time": "4:37", "title": "Many emitters!" },
    { "time": "5:58", "title": "Some exercises you could try." },
    { "time": "6:41", "title": "What's next?" }
  ],
  "canContribute": true,
  "codeExamples": [
    {
      "title": "Particle Emitters",
      "description": "Spawning a new particle emitter on clicking the screen",
      "image": "emitters.jpg",
      "urls": { "p5": "https://editor.p5js.org/codingtrain/sketches/YqAxA5CYy" }
    },
    {
      "title": "Particle Emitters with Movers Exercise",
      "description": "Adding fire particle effects to an array of movers",
      "image": "movers.jpg",
      "urls": { "p5": "https://editor.p5js.org/codingtrain/sketches/UXmqwcpRL" }
    },
    {
      "title": "Particles Following Mouse Exercise",
      "description": "Making a particle emitter that follows the mouse",
      "image": "mouse.jpg",
      "urls": { "p5": "https://editor.p5js.org/codingtrain/sketches/1zTN6PYJg" }
    },
    {
      "title": "Particle Emitters Color Exercise",
      "description": "Clicking on the screen to make a new emitter with a random color",
      "image": "color.jpg",
      "urls": { "p5": "https://editor.p5js.org/codingtrain/sketches/IYisp9xmJ" }
    }
  ],
  "groupLinks": [
    {
      "title": "Videos",
      "links": [
        {
          "title": "Angles and Rotation",
          "url": "/tracks/the-nature-of-code-2/noc/3-angles/1-angles-and-rotation",
          "description": "Nature of Code video on the basics of angles and rotation in p5.js"
        },
        {
          "title": "Fireworks!",
          "url": "/challenges/27-fireworks",
          "description": "July 4th themed Coding Challenge to build a fireworks simulation in p5.js and Processing"
        },
        {
          "title": "Inheritance in JavaScript",
          "url": "/tracks/topics-in-native-javascript/js/inheritance",
          "description": "Coding Train video on inheritance in Object-Oriented Programming and JavaScript ES6"
        },
        {
          "title": "Polymorphism in JavaScript",
          "url": "/tracks/topics-in-native-javascript/js/polymorphism",
          "description": "Coding Train video on polymorphism in Object-Oriented Programming and JavaScript ES6"
        }
      ]
    }
  ],
  "credits": [
    { "title": "Editing", "name": "Mathieu Blanchette" },
    { "title": "Animations", "name": "Jason Heglund" }
  ],
  "date": "2021-03-12"
}
