{
  "header": {
    "title": "All aboard!",
    "description": "Welcome to the Coding Train with Daniel Shiffman! A YouTube channel dedicated to learning creative coding through beginner-friendly projects."
  },
  "newToCoding": {
    "title": "New to coding?",
    "description": "All aboard the Coding Train with Daniel Shiffman, a YouTube channel dedicated to beginner-friendly.",
    "guideCta": {
      "text": "Don't know where to start?",
      "buttonText": "read getting started guide",
      "href": "/guides/getting-started"
    },
    "discordCta": {
      "text": "have questions?",
      "buttonText": "join community discord",
      "href": "/discord"
    }
  },
  "tracks": {
    "title": "Tracks",
    "description": "All aboard the Coding Train with Daniel Shiffman, a YouTube channel dedicated to beginner-friendly creative coding tutorials and challenges. All aboard the Coding Train with Daniel Shiffman.",
    "featured": ["code-programming-with-p5-js", "algorithmic-botany"],
    "tracksCta": {
      "text": "ready to learn? check out our most popular tracks",
      "buttonText": "go to tracks",
      "href": "/tracks"
    }
  },
  "challenges": {
    "title": "Challenges",
    "description": "Watch Daniel take on some viewer submitted Coding Challenges in p5.js and Processing. The challenges range from algorithmic art, machine learning, simulation, to generative poetry, and more.",
    "featured": [
      "170-monty-hall-problem",
      "169-pi-in-the-sky",
      "165-slide-puzzle"
    ],
    "challengesCta": {
      "text": "ready to explore? check out the newest challenges",
      "buttonText": "go to challenges",
      "href": "/challenges"
    }
  },
  "passengerShowcase": {
    "title": "Passenger showcase highlight",
    "featured": "challenges/163-bezier-curves/showcase/contribution2.json",
    "cta": {
      "text": "Do you want to see other people's work?",
      "buttonText": "Check out showcase highlight"
    }
  },
  "events": {
    "title": "Events",
    "comingEventsDescription": "Next Coding Train event!",
    "noEventsDescription": "Keep your eye out for events in the future!",
    "upcoming": [
      {
        "title": "PCD Copenhagen",
        "description": "Processing Community Day Copenhagen is a free, one-day event to celebrate the intersection of art and code.",
        "date": "2022-06-14",
        "time": "16:00 GMT+2",
        "host": "PCD Copenhagen",
        "type": "IRL",
        "url": "https://pcdcph.com/"
      }
    ]
  },
  "support": {
    "title": "Support",
    "description": "Support the Coding Train and potentially get access to a number of perks like member-only content.",
    "options": [
      {
        "text": "YouTube Membership",
        "href": "https://www.youtube.com/thecodingtrain/join",
        "buttonText": "Join membership"
      },
      {
        "text": "Patreon",
        "href": "https://www.patreon.com/codingtrain",
        "buttonText": "Join membership"
      },
      {
        "text": "GitHub Sponsorship",
        "href": "https://github.com/sponsors/shiffman",
        "buttonText": "Join sponsorship"
      },
      {
        "text": "Twitch Subscription",
        "href": "https://www.twitch.tv/subs/CodingTrainChooChoo",
        "buttonText": "Subscribe to channel"
      },
      {
        "text": "Nature of Code Book",
        "href": "https://natureofcode.com/",
        "buttonText": "Buy book"
      }
    ]
  }
}
