{
  "title": "Tic Tac Toe",
  "description": "This is a beginner-friendly challenge where I attempt to code a basic version of the game Tic-Tac-Toe using JavaScript and the p5.js library.",
  "videoNumber": "149",
  "videoId": "GTWrWM1UsnA",
  "nebulaSlug": "thecodingtrain-coding-challenge-149-tic-tac-toe",
  "date": "2019-07-24",
  "languages": ["p5.js"],
  "topics": ["beginners", "Tic-Tac-Toe game", "games"],
  "canContribute": true,
  "relatedChallenges": ["77-recursion", "154-tic-tac-toe-minimax", "163-bezier-curves"],
  "timestamps": [
    { "time": "0:00", "title": "Welcome!" },
    { "time": "0:54", "title": "Start coding" },
    { "time": "3:50", "title": "Drawing X and O" },
    { "time": "5:00", "title": "Let's diagram this!" },
    {
      "time": "8:46",
      "title": "Randomly choose the first player at the start of round"
    },
    { "time": "10:18", "title": "Drawing the grid" },
    {
      "time": "10:58",
      "title": "Each player places their symbol on a random spot"
    },
    { "time": "15:00", "title": "Check for a winner" },
    { "time": "18:44", "title": "Checking for equality of three elements" },
    { "time": "19:50", "title": "More bugs" },
    { "time": "21:01", "title": "Final Working Version! Show the winner" },
    { "time": "22:34", "title": "Thanks for watching!" }
  ],
  "codeExamples": [
    {
      "title": "Tic Tac Toe",
      "description": "Simple demonstration of the game Tic-Tac-Toe.",
      "image": "tictactoe.png",
      "urls": {
        "p5": "https://editor.p5js.org/codingtrain/sketches/5JngATm3c",
        "processing": "https://github.com/CodingTrain/Coding-Challenges/tree/main/149_Tic_Tac_Toe/Processing"
      }
    }
  ],
  "groupLinks": [
    {
      "title": "Videos",
      "links": [
        {
          "title": "Tic Tac Toe AI with Minimax Algorithm - Coding Challenge #154",
          "url": "/challenges/154-tic-tac-toe-minimax",
          "description": "Implementing a minimax algorithm to play Tic Tac Toe"
        },
        {
          "icon": "🔴",
          "title": "Livestream Archive",
          "url": "https://youtu.be/Y6cMTh2BODY",
          "description": "Livestream #181: Processing Library + Tic Tac Toe"
        }
      ]
    }
  ],
  "credits": [
    { "title": "Editing", "name": "Mathieu Blanchette" },
    { "title": "Animations", "name": "Jason Heglund" }
  ]
}
